README.rst
mailflash.py
setup.py
mailflash.egg-info/PKG-INFO
mailflash.egg-info/SOURCES.txt
mailflash.egg-info/dependency_links.txt
mailflash.egg-info/not-zip-safe
mailflash.egg-info/requires.txt
mailflash.egg-info/top_level.txt