Metadata-Version: 1.1
Name: mailflash
Version: 0.2.2
Summary: Simple library to send emails
Home-page: https://github.com/nicolas-van/mailflash
Author: Nicolas Vanhoren
Author-email: nicolas.vanhoren@gmail.com
License: BSD
Platform: any
Classifier: Intended Audience :: Developers
Classifier: License :: OSI Approved :: BSD License
Classifier: Operating System :: OS Independent
Classifier: Programming Language :: Python
Classifier: Topic :: Software Development :: Libraries :: Python Modules
